sn_stat/__init__.py
sn_stat/det_config.py
sn_stat/llr.py
sn_stat/rate.py
sn_stat/sampler.py
sn_stat/sig_calc.py
sn_stat/signals.py
sn_stat/test_llr.py
sn_stat/test_rate.py
sn_stat/test_shape.py
sn_stat-0.3.4.dist-info/LICENSE
sn_stat-0.3.4.dist-info/METADATA
sn_stat-0.3.4.dist-info/WHEEL
sn_stat-0.3.4.dist-info/top_level.txt
sn_stat-0.3.4.dist-info/RECORD
