Metadata-Version: 2.1
Name: sn-stat
Version: 0.3.4
Summary: Statistical methods for supernova neutrino detection
Author: Andrey Sheshukov
Author-email: ash@jinr.ru
License: GNU GPLv3
Requires-Python: >=3.7
License-File: LICENSE
Requires-Dist: numpy
Requires-Dist: scipy
Provides-Extra: doc
Requires-Dist: sphinx; extra == "doc"
Requires-Dist: sphinx-rtd-theme; extra == "doc"
Provides-Extra: test
Requires-Dist: pytest; extra == "test"
Requires-Dist: hypothesis; extra == "test"
Requires-Dist: flake8; extra == "test"
